nvifan/__init__.py
nvifan/main.py
nvifan/algorithm/__init__.py
nvifan/algorithm/fan_speed.py
nvifan/algorithm/test_liner.py
nvifan/config/__init__.py
nvifan/config/config.py
nvifan/monitor/__init__.py
nvifan/monitor/temperature_monitor.py
nvifan/nvi/__init__.py
nvifan/nvi/device_list.py
nvifan/nvi/fan_control.py
nvifan/tools/__init__.py
nvifan/tools/installer.py
nvifan/utils/__init__.py
nvifan/utils/command.py
nvifan/utils/logs.py
nvifan/utils/permission.py
nvifan/utils/yaml_parser.py
nvifan-1.3.0.dist-info/LICENSE
nvifan-1.3.0.dist-info/METADATA
nvifan-1.3.0.dist-info/WHEEL
nvifan-1.3.0.dist-info/entry_points.txt
nvifan-1.3.0.dist-info/top_level.txt
nvifan-1.3.0.dist-info/RECORD
