Metadata-Version: 2.1
Name: nvifan
Version: 1.3.0
Summary: A tool aimed at controlling NVIDIA GPU fans on Linux.
Home-page: https://github.com/a645162/nvidia-fan-control
Author: Haomin Kong
Author-email: a645162@gmail.com
License: GPLv3
Requires-Python: >=3.7
License-File: LICENSE
Requires-Dist: nvitop
Requires-Dist: chardet
Requires-Dist: PyYaml
Requires-Dist: loguru
